{"id":"33ce1b51-c592-4024-8040-fd2a26cb4b9b","name":"Avocado and Corn Sandwich","name_cn":"鳄梨玉米三明治","type":"Foods","type_cn":"食物","show_type_key":"Food","show_type":"Food","show_type_cn":"食物","product_type":"Food","product_sub_type":"Junk","class_des":null,"class_des_cn":null,"size":1,"grade":1,"can_buy":true,"can_sell":false,"can_rent":false,"commodity":false,"description":"NDR: 41\r\nEffects: None\r\nA rich, creamy avocado mash layered with a sweet and spicy corn salad and served on spelt bread. At Twyn's, it's what's inside that counts.","description_cn":"NDR：41\r\n效果：无\r\n浓厚奶油状鳄梨泥覆盖在甜辣的玉米沙拉佐以酸面包。吐温三明治，内在最重要。","shop_buy":[{"min_buying_price":null,"max_selling_price":null,"current_price":8.0,"layout_name":"Stanton-microTech-New Babbage-Twyns","layout_name_cn":"斯坦顿(Stanton)-微科星(microTech)-新巴贝奇(New Babbage)-Twyns","shop_inventory":1000.0,"shop_max_inventory":1000.0,"refresh_per_minute":50.0},{"min_buying_price":null,"max_selling_price":null,"current_price":8.0,"layout_name":"Stanton-Crusader-Orison-KelTo","layout_name_cn":"斯坦顿(Stanton)-十字军(Crusader)-奥里森(Orison)-KelTo","shop_inventory":1000.0,"shop_max_inventory":1000.0,"refresh_per_minute":50.0},{"min_buying_price":null,"max_selling_price":null,"current_price":8.0,"layout_name":"Stanton-Crusader-Orison-KetTo_Food","layout_name_cn":"斯坦顿(Stanton)-十字军(Crusader)-奥里森(Orison)-KetTo_Food","shop_inventory":1000.0,"shop_max_inventory":1000.0,"refresh_per_minute":50.0}],"shop_sell":[],"shop_rent":[],"file_name":"Data\\Libs\\Foundry\\Records\\Entities\\SCItem\\Carryables\\1H\\Food_sandwich_twyns_01_avocado_a.xml","json_path":"Data/Libs/Foundry/Records/Entities/SCItem/Carryables/1H/Food_sandwich_twyns_01_avocado_a.json"}