{"id":"1b64845a-42f1-48e8-960d-9a5099519b44","name":"Red Festival Envelope","name_cn":"红包","type":"Exchanging gilded red envelopes is one of the most popular ways of celebrating Red Festival. Often the envelope may include a small amount of credits inside to help those you care about have a strong start in the upcoming cycle. Growing in popularity is the newer tradition of hiding the envelopes as a way of spreading good fortune and prosperity to those that fate has deemed in need. \\n\\nStow the envelope as a token of luck, share it with a friend or loved one to spread good fortune, or exchange it at a commodities terminal and use the credits for a prosperous beginning to a new cycle.","type_cn":"交换烫金红包是庆祝火红最受欢迎的方式之一，通常人们会往红包内放入少量的信用点，祝愿亲朋好友新年行大运。并且近些年将红包藏起来的这种新传统愈发流行，人们希望借此来祝愿那些需要被命运眷顾的朋友们获得好运和健康。\\n\\n将红包当做好运的象征收藏起来吧，你也可以将它携带的好运分享给你的好友和爱人。亦或是去商品终端将其兑换成信用点当做是新年的第一笔收入。","show_type_key":"UNKNOWN","show_type":"Other","show_type_cn":"其它","product_type":"","product_sub_type":"","class_des":null,"class_des_cn":null,"size":null,"grade":null,"can_buy":false,"can_sell":true,"can_rent":false,"commodity":true,"description":null,"description_cn":null,"shop_buy":[],"shop_sell":[{"min_buying_price":null,"max_selling_price":500.0,"current_price":500.0,"layout_name":"Stanton-Crusader-Yela-Grim HEX-AdminOffice_Grimhex","layout_name_cn":"斯坦顿(Stanton)-十字军(Crusader)-耶拉(Yela)-六角湾(Grim HEX)-AdminOffice_Grimhex","shop_inventory":0.0,"shop_max_inventory":1000000.0,"refresh_per_minute":10000.0},{"min_buying_price":null,"max_selling_price":500.0,"current_price":500.0,"layout_name":"Stanton-Crusader-Orison-AdminOffice_Orison","layout_name_cn":"斯坦顿(Stanton)-十字军(Crusader)-奥里森(Orison)-AdminOffice_Orison","shop_inventory":0.0,"shop_max_inventory":1000000.0,"refresh_per_minute":10000.0},{"min_buying_price":null,"max_selling_price":500.0,"current_price":500.0,"layout_name":"Stanton-Hurston-Lorville-AdminOffice_Lorville","layout_name_cn":"斯坦顿(Stanton)-赫斯顿(Hurston)-罗威尔(Lorville)-AdminOffice_Lorville","shop_inventory":0.0,"shop_max_inventory":100000.0,"refresh_per_minute":1000.0},{"min_buying_price":null,"max_selling_price":500.0,"current_price":500.0,"layout_name":"Stanton-ArcCorp-Area18-AdminOffice_Area18","layout_name_cn":"斯坦顿(Stanton)-弧光星(ArcCorp)-18区(Area18)-AdminOffice_Area18","shop_inventory":0.0,"shop_max_inventory":1000000.0,"refresh_per_minute":50000.0},{"min_buying_price":null,"max_selling_price":500.0,"current_price":500.0,"layout_name":"Stanton-microTech-New Babbage-AdminOffice_NewBabbage","layout_name_cn":"斯坦顿(Stanton)-微科星(microTech)-新巴贝奇(New Babbage)-AdminOffice_NewBabbage","shop_inventory":0.0,"shop_max_inventory":100000.0,"refresh_per_minute":1000.0},{"min_buying_price":null,"max_selling_price":500.0,"current_price":500.0,"layout_name":"Stanton-microTech-New Babbage-AdminOffice_NewBabbage","layout_name_cn":"斯坦顿(Stanton)-微科星(microTech)-新巴贝奇(New Babbage)-AdminOffice_NewBabbage","shop_inventory":0.0,"shop_max_inventory":100000.0,"refresh_per_minute":1000.0},{"min_buying_price":null,"max_selling_price":500.0,"current_price":500.0,"layout_name":"Stanton-Crusader-PortOlisar-A-AdminOffice_PortO","layout_name_cn":"斯坦顿(Stanton)-十字军(Crusader)-奥丽莎空间站-A-AdminOffice_PortO","shop_inventory":0.0,"shop_max_inventory":1000000.0,"refresh_per_minute":10000.0},{"min_buying_price":null,"max_selling_price":500.0,"current_price":500.0,"layout_name":"Stanton-Crusader-PortOlisar-D-AdminOffice_PortO","layout_name_cn":"斯坦顿(Stanton)-十字军(Crusader)-奥丽莎空间站-D-AdminOffice_PortO","shop_inventory":0.0,"shop_max_inventory":1000000.0,"refresh_per_minute":10000.0},{"min_buying_price":null,"max_selling_price":500.0,"current_price":500.0,"layout_name":"Stanton-Crusader-PortOlisar-C-AdminOffice_PortO","layout_name_cn":"斯坦顿(Stanton)-十字军(Crusader)-奥丽莎空间站-C-AdminOffice_PortO","shop_inventory":0.0,"shop_max_inventory":1000000.0,"refresh_per_minute":10000.0},{"min_buying_price":null,"max_selling_price":500.0,"current_price":500.0,"layout_name":"Stanton-Crusader-PortOlisar-B-AdminOffice_PortO","layout_name_cn":"斯坦顿(Stanton)-十字军(Crusader)-奥丽莎空间站-B-AdminOffice_PortO","shop_inventory":0.0,"shop_max_inventory":1000000.0,"refresh_per_minute":10000.0}],"shop_rent":[],"file_name":"Data\\Libs\\Foundry\\Records\\Entities\\Commodities\\ConsumerGoods\\Special_HolidayLetter.xml","json_path":"Data/Libs/Foundry/Records/Entities/Commodities/ConsumerGoods/Special_HolidayLetter.json"}