{"id":"e533d75c-9275-48e9-bc93-f49a2c113bc5","name":"Breton","name_cn":"布列塔尼","type":"Power Plants","type_cn":"发电机","show_type_key":"PowerPlant","show_type":"PowerPlant","show_type_cn":"发电机","product_type":"PowerPlant","product_sub_type":"Power","class_des":" Industrial","class_des_cn":"工业","size":1,"grade":1,"can_buy":true,"can_sell":false,"can_rent":false,"commodity":false,"description":"Item Type: Power Plant\r\nManufacturer: Juno Starwerk\r\nSize: 1\r\nGrade: A\r\nClass: Industrial\r\nThe Breton embodies exactly what Juno Starwerk engineers wanted out of an industrial power plant — utilitarian, easy to repair and extremely powerful. You’ll be hard pressed to find a better balance of performance and durability from a unit this size.","description_cn":"物品类型：电源\r\n制造商：朱诺星际工厂(Juno Starwerk)\r\n尺寸：1\r\n等级：A\r\n类别：工业\r\n\"布列塔尼\"完全体现了朱诺星际工厂工程师们对工业电源的期望—实用，容易维修和性能强大。您很难从同尺寸的设备中找到除它以外能在性能与耐用性之间做出更好平衡的设备了。","shop_buy":[{"min_buying_price":null,"max_selling_price":null,"current_price":52600.0,"layout_name":"Stanton-ArcCorp-Area18-DumpersDepot_Area18","layout_name_cn":"斯坦顿(Stanton)-弧光星(ArcCorp)-18区(Area18)-DumpersDepot_Area18","shop_inventory":1000.0,"shop_max_inventory":1000.0,"refresh_per_minute":50.0},{"min_buying_price":null,"max_selling_price":null,"current_price":52600.0,"layout_name":"Stanton-microTech-New Babbage-OmegaPro_NewBabbage","layout_name_cn":"斯坦顿(Stanton)-微科星(microTech)-新巴贝奇(New Babbage)-OmegaPro_NewBabbage","shop_inventory":1000.0,"shop_max_inventory":1000.0,"refresh_per_minute":50.0},{"min_buying_price":null,"max_selling_price":null,"current_price":52600.0,"layout_name":"Stanton-Crusader-Orison-ShipWeaponsItems","layout_name_cn":"斯坦顿(Stanton)-十字军(Crusader)-奥里森(Orison)-ShipWeaponsItems","shop_inventory":100.0,"shop_max_inventory":100.0,"refresh_per_minute":1.0},{"min_buying_price":null,"max_selling_price":null,"current_price":52600.0,"layout_name":"Stanton-Crusader-Orison-ExpoHall_Fleetweek_Empty","layout_name_cn":"斯坦顿(Stanton)-十字军(Crusader)-奥里森(Orison)-ExpoHall_Fleetweek_Empty","shop_inventory":100.0,"shop_max_inventory":100.0,"refresh_per_minute":1.0}],"shop_sell":[],"shop_rent":[],"file_name":"Data\\Libs\\Foundry\\Records\\Entities\\SCItem\\Ships\\Powerplant\\POWR_JUST_S01_Breton_SCItem.xml","json_path":"Data/Libs/Foundry/Records/Entities/SCItem/Ships/Powerplant/POWR_JUST_S01_Breton_SCItem.json"}