{"id":"7ff2c313-51c7-459b-91e5-8afd089df32f","name":"Armada","name_cn":"舰队","type":"Shield Generators","type_cn":"护盾生成器","show_type_key":"Shield","show_type":"Shield","show_type_cn":"护盾生成器","product_type":"Shield","product_sub_type":"UNDEFINED","class_des":" Industrial","class_des_cn":"工业","size":2,"grade":4,"can_buy":true,"can_sell":false,"can_rent":false,"commodity":false,"description":"Item Type: Shield Generator\r\nManufacturer: Basilisk\r\nSize: 2\r\nGrade: D\r\nClass: Industrial\r\nBasilisk started by making cutting edge hull plating that was renowned for being durable and dependable. Today they carry on that proud legacy with industrial shield generators like the Armada. ","description_cn":"物品类型：护盾生成器\r\n制造商：毒蜥公司(Basilisk)\r\n尺寸：2\r\n等级：D\r\n类别：工业\r\n毒蜥公司最先采用了尖端的设备电镀技术，使其一直以来都以耐用和可靠而闻名。如今，他们的\"舰队\"等工业型护盾生成器继承了这一引以为傲的传统。","shop_buy":[{"min_buying_price":null,"max_selling_price":null,"current_price":29000.0,"layout_name":"Stanton-ArcCorp-Baijini Point-PlatinumBay_Stanton3_LEO1","layout_name_cn":"斯坦顿(Stanton)-弧光星(ArcCorp)-拜基尼空间站-PlatinumBay_Stanton3_LEO1","shop_inventory":1000.0,"shop_max_inventory":1000.0,"refresh_per_minute":50.0},{"min_buying_price":null,"max_selling_price":null,"current_price":29000.0,"layout_name":"Stanton-CRU L5-LRR_S2_L5-Galleria-PlatinumBay_Stanton2_L5","layout_name_cn":"斯坦顿(Stanton)-十-L5-LRR_S2_L5-购物中心-PlatinumBay_Stanton2_L5","shop_inventory":1000.0,"shop_max_inventory":1000.0,"refresh_per_minute":50.0},{"min_buying_price":null,"max_selling_price":null,"current_price":29000.0,"layout_name":"Stanton-Crusader-Yela-Grim HEX-DumpersDepot_GrimHEX","layout_name_cn":"斯坦顿(Stanton)-十字军(Crusader)-耶拉(Yela)-六角湾(Grim HEX)-DumpersDepot_GrimHEX","shop_inventory":1000.0,"shop_max_inventory":1000.0,"refresh_per_minute":50.0},{"min_buying_price":null,"max_selling_price":null,"current_price":29000.0,"layout_name":"Stanton-HUR L3-LRR_S1_L3-Galleria-PlatinumBay_Stanton1_L3","layout_name_cn":"斯坦顿(Stanton)-赫-L3-LRR_S1_L3-购物中心-PlatinumBay_Stanton1_L3","shop_inventory":1000.0,"shop_max_inventory":1000.0,"refresh_per_minute":50.0}],"shop_sell":[],"shop_rent":[],"file_name":"Data\\Libs\\Foundry\\Records\\Entities\\SCItem\\Ships\\ShieldGenerator\\SHLD_BASL_S02_Armada_SCItem.xml","json_path":"Data/Libs/Foundry/Records/Entities/SCItem/Ships/ShieldGenerator/SHLD_BASL_S02_Armada_SCItem.json"}