{"id":"14d6ba03-86ad-47f8-b940-e8a82d2d52b6","name":"Greycat ROC-DS","name_cn":"灰猫 ROC-DS","type":"Ground Vehicles","type_cn":"地面载具","show_type_key":"NOITEM_Vehicle","show_type":"Vehicle","show_type_cn":"载具","product_type":"NOITEM_Vehicle","product_sub_type":"Vehicle_GroundVehicle","class_des":null,"class_des_cn":null,"size":1,"grade":1,"can_buy":true,"can_sell":false,"can_rent":true,"commodity":false,"description":"Manufacturer: Greycat Industrial\r\nFocus: Mining\r\nBy focusing on the essentials of terrestrial-based mining, Greycat Industrial designed their hardworking, no-nonsense ROC-DS (Remote Ore Collector Dual Seat) to let mining pairs do more while in the field. The ROC-DS raises the ground-mining game by adding extra cargo capacity and a second seat to operate the precision gimbaled mining arm. Greycat even upgraded the driver's cab with a protective enclosure to allow for longer excursions in harsh conditions. With the ROC-DS, mining duos now have the right tool to comfortably collect more ore. ","description_cn":"制造商：灰猫工业\r\n定位：采矿\r\n灰猫工业专注于地面采矿的本质，设计出了勤劳、务实的ROC-DS（远程矿石收集者双座版），使得采矿二人组们在作业现场能够做到事半功倍。通过增添额外的货舱容量，以及用于操控精密可动矿臂的副座，ROC-DS提升了地面采矿的作业体验。灰猫甚至使用防护屏对驾驶室进行了升级，使得恶劣环境下的作业活动能够更加持久。有了ROC-DS，采矿二人组便拥有了合适的工具来舒适地采集更多矿石。","shop_buy":[{"min_buying_price":null,"max_selling_price":null,"current_price":176500.0,"layout_name":"Stanton-Hurston-Lorville-NewDeal_Lorville","layout_name_cn":"斯坦顿(Stanton)-赫斯顿(Hurston)-罗威尔(Lorville)-NewDeal_Lorville","shop_inventory":100.0,"shop_max_inventory":100.0,"refresh_per_minute":1.0}],"shop_sell":[],"shop_rent":[{"min_buying_price":null,"max_selling_price":null,"current_price":176500.0,"layout_name":"Stanton-microTech-New Babbage-BestInShow_Kiosk","layout_name_cn":"斯坦顿(Stanton)-微科星(microTech)-新巴贝奇(New Babbage)-BestInShow_Kiosk","shop_inventory":10000.0,"shop_max_inventory":10000.0,"refresh_per_minute":100.0,"rent_price1":null,"rent_price3":null,"rent_price3_per_day":null,"rent_price7":null,"rent_price7_per_day":null,"rent_price30":null,"rent_price30_per_day":null},{"min_buying_price":null,"max_selling_price":null,"current_price":176500.0,"layout_name":"Stanton-microTech-New Babbage-ARGO_CNOU_GRIN_KRIG","layout_name_cn":"斯坦顿(Stanton)-微科星(microTech)-新巴贝奇(New Babbage)-ARGO_CNOU_GRIN_KRIG","shop_inventory":10000.0,"shop_max_inventory":10000.0,"refresh_per_minute":100.0,"rent_price1":null,"rent_price3":null,"rent_price3_per_day":null,"rent_price7":null,"rent_price7_per_day":null,"rent_price30":null,"rent_price30_per_day":null}],"file_name":"Data\\Libs\\Foundry\\Records\\Entities\\GroundVehicles\\GRIN_ROC_DS.xml","json_path":"Data/Libs/Foundry/Records/Entities/GroundVehicles/GRIN_ROC_DS.json"}