{"id":"6a6f3e8f-8c0d-49c0-8813-d44072cd573a","name":"Prim Shoes Twilight","name_cn":"正装鞋 暮光色","type":"Footwear","type_cn":"鞋子","show_type_key":"Char_Clothing_Feet","show_type":"Char_Clothing_Feet","show_type_cn":"鞋子","product_type":"Char_Clothing_Feet","product_sub_type":"UNDEFINED","class_des":null,"class_des_cn":null,"size":1,"grade":1,"can_buy":true,"can_sell":false,"can_rent":false,"commodity":false,"description":"Professional yet casual, the Prim utilizes cutting-edge synthetic construction to provide maximum comfort and a shine that won't fade. ","description_cn":"专业且休闲，正装鞋使用先进的合成结构提供最大的舒适度和永不褪色的光泽。","shop_buy":[{"min_buying_price":null,"max_selling_price":null,"current_price":260.0,"layout_name":"Stanton-Hurston-Everus Harbor-CasabaOutlet_Stanton1_LEO1","layout_name_cn":"斯坦顿(Stanton)-赫斯顿(Hurston)-埃弗勒斯空间站-CasabaOutlet_Stanton1_LEO1","shop_inventory":1000.0,"shop_max_inventory":1000.0,"refresh_per_minute":50.0}],"shop_sell":[],"shop_rent":[],"file_name":"Data\\Libs\\Foundry\\Records\\Entities\\SCItem\\Characters\\Human\\Clothing\\PU_Clothing\\Clothing_Feet\\fio_shoes_01_01_18.xml","json_path":"Data/Libs/Foundry/Records/Entities/SCItem/Characters/Human/Clothing/PU_Clothing/Clothing_Feet/fio_shoes_01_01_18.json"}