{"id":"34506e83-b7b8-4804-a7bb-f31f11bb9214","name":"C.O. Nomad","name_cn":"联合外域 游牧者","type":"ship","type_cn":"飞船","show_type_key":"NOITEM_Vehicle","show_type":"Vehicle","show_type_cn":"载具","product_type":"NOITEM_Vehicle","product_sub_type":"Vehicle_Spaceship","class_des":null,"class_des_cn":null,"size":2,"grade":1,"can_buy":true,"can_sell":false,"can_rent":false,"commodity":false,"description":"Manufacturer: Consolidated Outland \r\nFocus: Light Freight\r\nWith the versatility of a medium-sized multi-purpose freighter packed into a stylish, compact frame, the Consolidated Outland Nomad is the model of self-sufficiency, the spirit of the open sky, and the perfect solution for anyone yearning to start a brand-new adventure.","description_cn":"制造商：联合外域(Consolidated Outland)\r\n定位：轻型货运\r\n一艘中型多用途运输船包装在了一个时尚、紧凑的框架中，联合外域游牧者是自给自足的典范，是开阔天空的灵魂，是所有渴望展开全新冒险的人们的完美解决方案。","shop_buy":[{"min_buying_price":null,"max_selling_price":null,"current_price":952800.0,"layout_name":"Stanton-Hurston-Lorville-NewDeal_Lorville","layout_name_cn":"斯坦顿(Stanton)-赫斯顿(Hurston)-罗威尔(Lorville)-NewDeal_Lorville","shop_inventory":100.0,"shop_max_inventory":100.0,"refresh_per_minute":1.0}],"shop_sell":[],"shop_rent":[],"file_name":"Data\\Libs\\Foundry\\Records\\Entities\\Spaceships\\CNOU_Nomad.xml","json_path":"Data/Libs/Foundry/Records/Entities/Spaceships/CNOU_Nomad.json"}